MANIFEST.in
README.rst
ez_setup.py
requirements.txt
setup.py
Beeswarm.egg-info/PKG-INFO
Beeswarm.egg-info/SOURCES.txt
Beeswarm.egg-info/dependency_links.txt
Beeswarm.egg-info/requires.txt
Beeswarm.egg-info/top_level.txt
beeswarm/__init__.py
beeswarm/__init__.pyc
beeswarm/errors.py
beeswarm/errors.pyc
beeswarm/drones/__init__.py
beeswarm/drones/__init__.pyc
beeswarm/drones/drone.py
beeswarm/drones/client/__init__.py
beeswarm/drones/client/__init__.pyc
beeswarm/drones/client/client.py
beeswarm/drones/client/client.pyc
beeswarm/drones/client/baits/__init__.py
beeswarm/drones/client/baits/__init__.pyc
beeswarm/drones/client/baits/clientbase.py
beeswarm/drones/client/baits/clientbase.pyc
beeswarm/drones/client/baits/ftp.py
beeswarm/drones/client/baits/ftp.pyc
beeswarm/drones/client/baits/http.py
beeswarm/drones/client/baits/http.pyc
beeswarm/drones/client/baits/https.py
beeswarm/drones/client/baits/https.pyc
beeswarm/drones/client/baits/pop3.py
beeswarm/drones/client/baits/pop3.pyc
beeswarm/drones/client/baits/pop3s.py
beeswarm/drones/client/baits/pop3s.pyc
beeswarm/drones/client/baits/smtp.py
beeswarm/drones/client/baits/smtp.pyc
beeswarm/drones/client/baits/ssh.py
beeswarm/drones/client/baits/ssh.pyc
beeswarm/drones/client/baits/telnet.py
beeswarm/drones/client/baits/telnet.pyc
beeswarm/drones/client/baits/vnc.py
beeswarm/drones/client/baits/vnc.pyc
beeswarm/drones/client/baits/shared/__init__.py
beeswarm/drones/client/baits/shared/__init__.pyc
beeswarm/drones/client/baits/shared/shell.py
beeswarm/drones/client/baits/shared/shell.pyc
beeswarm/drones/client/models/__init__.py
beeswarm/drones/client/models/__init__.pyc
beeswarm/drones/client/models/dispatcher.py
beeswarm/drones/client/models/dispatcher.pyc
beeswarm/drones/client/models/session.py
beeswarm/drones/client/models/session.pyc
beeswarm/drones/client/tests/__init__.py
beeswarm/drones/client/tests/__init__.pyc
beeswarm/drones/client/tests/dummy_cert.crt
beeswarm/drones/client/tests/dummy_key.key
beeswarm/drones/client/tests/test_client.py
beeswarm/drones/client/tests/test_client.pyc
beeswarm/drones/client/tests/test_feeder.py
