Metadata-Version: 1.0
Name: Beeswarm
Version: 0.7.18
Summary: Honeytoken transmission, reception and analysis.
Home-page: https://github.com/honeynet/beeswarm
Author: Johnny Vestergaard, The Honeynet Project
Author-email: jkv@unixcluster.dk
License: GPL 3
Platform: UNKNOWN
